{
  "id": "tag:blogger.com,1999:blog-3116858574126921604.post-420417457655520603",
  "title": "Git core commands for code Syncing",
  "slug": "git-core-commands-for-code-syncing",
  "updated": "2026-06-12T11:14:33.839+05:30",
  "author": "Priya",
  "labels": [
    "Cloud DevOps | GitOps interview questions"
  ],
  "content": "<div class=\"my-top-header\">\n\n  <h1>INTERVIEW PREPS</h1>\n\n  <div class=\"my-top-links\">\n\n    <a href=\"/search/\">All</a>\n\n    <a href=\"/search/label/Java interview Questions\">? Java</a>\n\n    <a href=\"/search/label/Spring interview Questions\">? Spring</a>\n\n    <a href=\"/search/label/Android interview Questions\">? Android</a>\n\n    <a href=\"/search/label/PHP web development Questions\">? PHP</a>\n\n    <a href=\"/p/all-spoken-english-content.html\">? English</a>\n\n    <a href=\"/search/label/HR | Managerial interview Questions\">? HR</a>\n\n    <a href=\"/search/label/Cloud DevOps | GitOps interview questions\">? DevOps</a>\n\n    <a href=\"/search/label/Technical interview questions\">? Technical</a>\n\n  </div>\n\n</div>\n\n<style>\n \n/* FORCE FULL PAGE WIDTH */\n\nbody,\nbody .content,\nbody .content-outer,\nbody .main-outer,\nbody .main-inner,\nbody .columns,\nbody .post-outer,\nbody .post,\nbody .post-body,\nbody .centered,\nbody .page,\nbody .page_body,\nbody .widget,\nbody .section{\n\n    width:100% !important;\n    max-width:100% !important;\n    min-width:100% !important;\n\n    margin:0 !important;\n    padding:0 !important;\n\n    left:0 !important;\n    right:0 !important;\n\n    transform:none !important;\n}\nhtml{\n  scroll-behavior:smooth;\n}\n\nbody{\n  margin:0;\n  padding:0;\n  font-family:Arial,sans-serif;\n  background:#111;\n  overflow-x:hidden;\n}\n\n/* FORCE BLOGGER TO STOP CENTER ALIGNING */\n\n.post,\n.post-body,\n.post-outer,\n.content,\n.content-inner,\n.main-inner,\n.main-outer,\n.region-inner,\n.columns{\n  margin-left:0 !important;\n  margin-right:0 !important;\n\n  transform:none !important;\n}\n/* HIDE BLOGGER HEADER */\n\nheader,\n.header,\n#header,\n.Header,\n.header-widget{\n  display:none !important;\n}\n\n/* SIDEBAR */\n\n.sidebar{\n    position:fixed;\n    top:0;\n    left:0;\n    width:220px;\n    height:100vh;\n    overflow-y:auto;\n    background:#651313;\n    z-index:9999;\n}\n\n.sidebar h2{\n  color:#ff6a00;\n  text-align:center;\n  margin:20px 0;\n}\n\n.sidebar ul{\n  list-style:none;\n  padding:0;\n  margin:0;\n}\n\n.sidebar li{\n  margin:0;\n}\n\n.sidebar a{\n  display:block;\n  padding:14px 18px;\n  color:#fff;\n  text-decoration:none;\n  font-size:18px;\n}\n\n.sidebar a:hover{\n  background:#ff5a00;\n}\n\n/* MAIN CONTENT */\n\n.main{\n    margin-left:220px;\n   \n    width:calc(100% - 220px);\n\n    padding:15px;\n    box-sizing:border-box;\n}\n  html,\nbody{\n  width:100%;\n  overflow-x:hidden;\n}\n  .main,\n.post,\n.post-body,\n.post-outer{\n  max-width:none !important;\n}\n  .post-body{\n  width:100% !important;\n  max-width:100% !important;\n}\n/* SECTIONS */\n\nsection{\n    width:100%;\n    box-sizing:border-box;\n\n    padding:25px;\n    margin-bottom:20px;\n\n    background:#f3e3e7;\n    color:#111;\n\n    border-radius:14px;\n}\n/* TEXT */\n\nsection h1,\nsection h2{\n  color:#5a1111;\n  font-size:38px;\n  margin-bottom:20px;\n}\n\nsection p,\nsection li,\nsection b{\n  font-size:22px;\n  line-height:1.8;\n}\n\n/* CODE */\n\npre,\ncode{\n  white-space:pre-wrap;\n  word-break:break-word;\n}\n  /*\ntable{\n  display:block;\n  width:100%;\n  max-width:100%;\n  overflow-x:auto;\n\n  border-collapse:collapse;\n}\n\ntable td,\ntable th{\n\n  white-space:nowrap;\n\n  padding:10px;\n  border:1px solid #555;\n}\n*/\n  table{\n    width:100% !important;\n    table-layout:fixed !important;\n    border-collapse:collapse;\n}\n\ntable td,\ntable th{\n    white-space:normal !important;\n    word-break:break-word !important;\n    overflow-wrap:anywhere !important;\n    padding:10px;\n    border:1px solid #555;\n}\n\n/* MOBILE */\n\n@media(max-width:768px){\n\n.sidebar{\n  position:relative;\n  width:100%;\n  height:250px;\n}\n\n.main{\n  margin-left:0;\n  width:100%;\n}\n\nsection{\n  padding:18px;\n}\n\nsection h1,\nsection h2{\n  font-size:30px;\n}\n\nsection p,\nsection li,\nsection b{\n  font-size:18px;\n}\n\n}\n\n  /* FINAL BLOGGER WIDTH FIX */\n\nbody .main-wrapper,\nbody .main-outer,\nbody .content-outer,\nbody .content-fauxcolumn-outer,\nbody .region-inner,\nbody .columns,\nbody .post-outer,\nbody .centered,\nbody .page_body,\nbody .content-wrapper{\n\n    width:100vw !important;\n    max-width:100vw !important;\n\n    margin:0 !important;\n    padding:0 !important;\n\n    left:0 !important;\n    right:0 !important;\n}\n  \n  \n  /* SHIFT FOOTER RIGHT */\n\nfooter,\n.footer,\n.footer-outer,\n.footer-inner,\n#footer,\n.bottom,\n.bottommenu{\n\n    margin-left:80px !important;\n\n    width:calc(100% - 220px) !important;\n\n    box-sizing:border-box !important;\n}\n \n  \n.sidebar p,\n.sidebar li,\n.sidebar span,\n.sidebar a,\n.sidebar .widget-content {\n  font-size: 13px !important;\n  line-height: 1.6;\n}\n  \n\n   /*reducing font size of content not sidebar */\n  .post-body p,\n.post-body li,\n.post-body span,\n.post-body div {\n  font-size: 14px !important;\n  line-height: 1.7;\n}\n\n\n  /* reducing sidebar font */\n  .sidebar-container p,\n.sidebar-container li,\n.sidebar-container span,\n.sidebar-container a {\n  font-size: 13px !important;\n}\n  /* NEW CUSTOM HEADER */\n\n.my-top-header{\n    position:fixed !important;\n\n    top:0 !important;\n    left:220px !important;   /* same as sidebar width */\n\n    width:calc(100% - 220px) !important;\n\n    background:#111;\n\n    text-align:center !important;\n\n    z-index:99999 !important;\n\n    padding:6px 10px !important;\n    box-sizing:border-box !important;\n}\n\n.my-top-header h1{\n    margin:0 !important;\n    text-align:center !important;\n    font-size:24px !important;\n}\n\n.my-top-links{\n    display:flex !important;\n    justify-content:center !important;\n    align-items:center !important;\n}\n/* push the page content down */\n  .main,\n.main-wrapper,\n.content-outer{\n    padding-top:70px !important;\n}\n  /* HIDE BLOGGER NAV BAR */\n\nnav,\n.navigation,\n.navbar,\n.tabs,\n.tabs-outer,\n.tabs-inner,\n.menu,\n.menu-wrapper,\n.PageList,\n#PageList1{\n    display:none !important;\n}\n\n/* FIXED CUSTOM HEADER */\n\n.my-top-header{\n    position:fixed !important;\n    top:0 !important;\n    left:220px !important;   /* sidebar width */\n\n    width:calc(100% - 220px) !important;\n\n    background:#111;\n    z-index:99999;\n\n    text-align:center;\n    padding:6px 10px;\n    box-sizing:border-box;\n}\n\n\n\n\n/* MOBILE */\n\n@media (max-width:768px){\n\n    .my-top-header{\n        left:0 !important;\n        width:100% !important;\n    }\n\n    .my-top-header h1{\n        font-size:18px !important;\n    }\n\n    .my-top-links{\n        justify-content:flex-start !important;\n        overflow-x:auto !important;\n    }\n}\n  @media (max-width:768px){\n\n    .my-top-header{\n        left:0 !important;\n        width:100% !important;\n    }\n\n    .post-title-container{\n        left:0 !important;\n        width:100% !important;\n        top:50px !important;\n    }\n\n    .main{\n        padding-top:100px !important;\n    }\n     .post-title-container{\n        margin-left:0 !important;\n        width:100% !important;\n    }\n}\n  /* ORANGE TITLE BAR TEXT FIX */\n\n.post-title,\n.post-title a,\nh3.post-title,\n.post-title.entry-title{\n\n    font-weight:700 !important;\n    text-align:left !important;\n\n    font-size:18px !important;\n    line-height:1.3 !important;\n\n    padding-left:12px !important;\n\n    color:#fff !important;\n}\n  /* Main page title half hidden behind sidebar */\n  .post-title-container{\n    margin-left:220px !important;\n    width:calc(100% - 220px) !important;\n    box-sizing:border-box !important;\n}\n  /* orange bar text changed from white to black */\n  .post-title,\n.post-title a,\nh3.post-title.entry-title{\n    color:#000 !important;\n    text-align:left !important;\n    padding-left:15px !important;\n    font-weight:700 !important;\n}\n \n /* moving my popular post ,followers ,comment to right */ \n  .post-content-container,\n.post-title-container,\n.post-outer,\n.feed-view,\n.blog-posts,\n.widget-content,\n.PopularPosts,\n.Followers,\n.followers,\n.followers-widget,\n#Followers1,\n#followers,\n#comments,\n.comments{\n\n    left:auto !important;\n    margin-left:0 !important;\n    position:relative !important;\n}\n  \n  /* Orange title bar not visible on first load (mobile) */\n  @media (max-width:768px){\n\n  .post-title-container{\n      position:relative !important;\n      top:auto !important;\n      left:auto !important;\n      z-index:auto !important;\n\n      width:100% !important;\n      margin:0 !important;\n\n      display:block !important;\n      visibility:visible !important;\n  }\n\n}\n  \n  footer,\n.custom-footer,\n#comments,\n.comments,\n.Followers,\n.followers,\n.followers-widget,\n#Followers1,\n#followers,\n.PopularPosts,\n.related-posts{\n\n    margin-left:220px !important;\n    width:calc(100% - 220px) !important;\n\n    left:auto !important;\n    right:auto !important;\n    position:relative !important;\n\n    box-sizing:border-box !important;\n}\n  @media(max-width:768px){\n\n    footer,\n    .custom-footer,\n    #comments,\n    .comments,\n    .Followers,\n    .followers,\n    .followers-widget,\n    #Followers1,\n    #followers,\n    .PopularPosts,\n    .related-posts{\n\n        margin-left:0 !important;\n        width:100% !important;\n        left:auto !important;\n    }\n}\n  \n  .PopularPosts,\n#PopularPosts1{\n    display:none !important;\n}\n  /* Orange title bar not visible until scrolling */\n  .post-title-container{\n    display:block !important;\n    visibility:visible !important;\n    opacity:1 !important;\n\n    position:fixed !important;\n    top:70px !important;   /* adjust to your header height */\n    left:220px !important;\n    right:0 !important;\n\n    z-index:9998 !important;\n}\n  .main{\n    padding-top:60px !important;\n}\n  @media(max-width:768px){\n\n    .post-title,\n    .post-title a,\n    h3.post-title.entry-title{\n        padding-left:10px !important;\n        font-size:14px !important;\n    }\n\n}\n</style>\n\n<a id=\"quizBtn\">\n  Take Quiz\n</a>\n\n<script>\nconst postId =\ndocument.body.dataset.postid;\nfunction saveLocalQuiz(\narticleKey,\nquestions\n){\n\nlocalStorage.setItem(\narticleKey,\nJSON.stringify(\nquestions\n)\n);\n\n}\n\n  document.getElementById(\"quizBtn\").href =\n\"/p/quiz.html?url=\" +\nencodeURIComponent(\nwindow.location.href\n);\n  \n</script>\n\n<div class=\"sidebar\">\n  <h2>Git Commands</h2>\n\n<ul>\n  <li><a href=\"#j1\"><i class=\"fas fa-code\"></i> Git Commands while pushing code to a new repo.</a></li>\n\n<li><a href=\"#j2\"><i class=\"fas fa-code\"></i> Git Commands while pushing code to an existing repo</a></li>\n\n<li><a href=\"#j3\"><i class=\"fas fa-database\"></i> Steps to copy a project from remote branch</a></li>\n\n<li><a href=\"#j4\"><i class=\"fas fa-bug\"></i>  When your local branch is ahead of remote branch by 1 commit</a></li>\n  <li><a href=\"#j5\"><i class=\"fas fa-bug\"></i> To delete a remote Branch </a></li>\n\n<li><a href=\"#j6\"><i class=\"fas fa-cubes\"></i> When code is not getting pushed to remote Branch</a></li>\n  <li><a href=\"#j7\"><i class=\"fas fa-cubes\"></i>   Rebase Vs Merge</a></li>\n  \n<li><a href=\"#j8\"><i class=\"fas fa-cubes\"></i> How to push some changes to remote branch</a></li>\n\n<li><a href=\"#j9\"><i class=\"fas fa-layer-group\"></i> Commit without any commit message</a></li>\n\n<li><a href=\"#j10\"><i class=\"fas fa-sitemap\"></i> fast-forward merge</a></li>\n\n<li><a href=\"#j11\"><i class=\"fas fa-bolt\"></i> no-fast-forward</a></li>\n\n<li><a href=\"#j12\"><i class=\"fas fa-project-diagram\"></i> reflog </a></li>\n\n<li><a href=\"#j13\"><i class=\"fas fa-microchip\"></i>  --force </a></li>\n\n  <li><a href=\"#j14\"><i class=\"fas fa-code\"></i>   Git(Distributed VCS) Vs SVN(centralized VCS)</a></li>\n  <li><a href=\"#j15\"><i class=\"fas fa-layer-group\"></i>   Gitlab over Github</a></li>\n\n<li><a href=\"#j16\"><i class=\"fas fa-sitemap\"></i>     Putty</a></li>\n\n<li><a href=\"#j17\"><i class=\"fas fa-bolt\"></i>   Git Vs SourceTree</a></li>\n\n</ul>\n\n</div>\n\n<!-- Main Content -->\n\n<div class=\"main\">\n  \n  <section id=\"j1\">\n       <h1>Git Commands while pushing code to a new repo</h1>\n   - git init<br>\n   - git add .<br>\n   - git commit -m \"commit message\"<br>\n   - git remote add origin \"url of the remote repository\"<br>\n   - git push origin master\n  </section>\n   <section id=\"j2\">\n        <h1>Git Commands while pushing code to an existing repo</h1>\n   - git init<br>\n   - git add -A<br>\n   - git commit -m \"commit message\"<br>\n   - git push origin master\n  </section>\n   <section id=\"j3\">\n         <h1>Steps to copy a project from remote branch</h1>\n   - git init<br>\n   - git add .<br>\n   - git clone \"Link of the repository from remote\"<br>\n \n  </section>\n   <section id=\"j4\">\n         <h1>When your local branch is ahead of remote branch by 1 commit</h1>\n   - git pull<br>\n   - git checkout -b newBranchName<br>\n   - git pull origin remoteBranchName<br>\n   - git status<br>\n    <h4>Problem solved for the newBranchName which u have created above</h4> \n \n  </section>\n   <section id=\"j5\">\n         <h1>To delete a remote Branch</h1>\n    git push origin --delete remoteBranchName\n \n  </section>\n    <section id=\"j6\">\n         <h1>When code is not getting pushed to remote Branch</h1>\n   After using git push origin master <h4>when code is not \n   getting pushed and instead you r getting message as \"remote\n   end hung up unexpectedly.Than use :\"\n                                        </h4><br>\n   git push origin master --force <br>\n   <h4>If this command doesn't work than use different commit and push as:</h4>\n   git commit --amend -m \"commit message\"<br>\n   git push \n \n  </section>\n    <section id=\"j7\">\n         <h1>Rebase Vs Merge</h1>\n      <b>Rebase</b> deletes all commit history for the new feature branch.Rebasing \n    makes the branching history cleaner and with more linear  commits repo structure .<br>\n      with <b>git merge</b> , we merge changes of 2 branches , but rather than deleting old commits  \n      of feature branch , it creates new commit and merge changes of both the branches. and if feature branch wants to rollback to \n      previous commit it can easily do so incase of merge but not in rebase.\n      \n      <table border=2>\n        <tr>\n          <td><b>Sno.</b></td><td><b>Merge</b></td><td><b>Rebase</b></td>\n        </tr>\n        <tr>\n          <td>1</td><td>Create new commits while integrating changes from 1 branch to another</td>\n          <td>Doesn't create any new commits while integrating changes from 1 branch to another.</td>\n        </tr>\n        <tr>\n          <td>2</td><td>It is safe in nature as it does not re-write the history of your feature branch.</td>\n          <td>It is destructive in nature.ie... if u rebase feature branch with latest change in master branch ,feature branch commit hashes r changed.</td>\n        </tr>\n        <tr>\n          <td>3</td><td>WHen feature branch is in remote and someone else is creating new branch on top of your feature branch , use git merge to get changes from master to feature</td>\n          <td>When feature branch is local and changing history will not affect other branches. use git rebase to take changes from master in feature branch.</td>\n        </tr>\n        \n        </table>\n Rebase replaces commits of feature branch in top of master in a linear fashion. The old, orphaned commits remain in your Git reflog and aren't permanently deleted until they are garbage-collected\n  </section>\n   <section id=\"j8\">\n        <h1>How to push some changes to remote branch</h1>\n     - git checkout -b [branchname]<br>\n     - git push -u origin [branchname]<br>\n  </section>\n   <section id=\"j9\">\n        <h1>Commit without any commit message</h1>\n     git commit -am ''<br>\n     you will see that it fails because an empty commit message is not allowed. Newer versions of git have the\n     --allow-empty-message commandline argument, including the version of git included with the latest version of \n     Xcode. This will let you use this command to make a commit with an empty message:<br>\n     git commit -a --allow-empty-message -m '  '<br>\n                                 Or\n     git commit -am'.' <br>\n              or shorter:<br>\n     git commit -am. <br>\n     This adds a commit with the message .<br>\n  </section>\n   <section id=\"j10\">\n        <h1>fast-forward merge</h1>\n       A fast-forward merge can never have a merge conflict because Git won't apply a \n                            fast-forward merge if the tip of the target branch has diverged from the source branch.<br>\n                           git merge master (by default treated as fast forward )<br>\n                          A fast forward merge is when we merge a branch that is ahead of our checked out branch.<br>\nFast forward merge creates a linear history after the merge eliminating all the branching scenarios. \nAll the commits of master &amp; feature branch will synchronised into 1. Both master &amp; feature will show \nthe common branch history all the way through..<br>\noption --no-ff (i.e. true merge) creates a new commit with multiple parents, and provides a better history tracking. <br>\nOtherwise, --ff (i.e. fast-forward merge) is by default.<br>\nIf we want to reuse the commits of feature branch than good to use --no-ff flag otherwise can work \nwith default fast forward option when changes from feature branch r merged to master and feature \nbranch commits r of no further use.<br>\n\n  </section>\n   <section id=\"j11\">\n        <h1>no fast-forward merge</h1>\n       The no-fast-forward merge is also known as a three-way merge or true merge.\n                                git merge master --no-ff (no fast forward)<br>\n                                option --no-ff (i.e. true merge) creates a new commit with multiple parents, \n                                and provides a better history tracking. <br>\n                                Otherwise, --ff (i.e. fast-forward merge) is by default.<br>\n                                If we want to reuse the commits of feature branch than good to use --no-ff flag<br>\n\n  </section>\n   <section id=\"j12\">\n        <h1>reflog</h1>\n        Once we did git reset --hard all our latest changes removed permanently \n                                but after using this command their is still a way to regain those \n                                changes by using -><br>\n                                git reflog<br>\n                                git checkout -b  \"any new branch name\" \"sha of the commit we destroyed\"<br>\n                       So, we have now resurrected that commit.commits actually don't get destroyed for some \n                       90 days.so, we can undo any commit changes we have removed<br><br>\n\n  </section>\n    <section id=\"j13\">\n        <h4 class=\"card-text\">git push origin master -- force</h4>\n         When code is not getting pushed to remote branch after using git push \n                                origin master or getting message as remote end hung up unexpectedly than use :<br>\n                                git push origin master -- force<br>\n                                If this command don't work than<br>\n                                Use d/f commit than push as :<br>\n                                git commit --amend -m \"mssg\"<br>\n                                git push<br><br>\n\n  </section>\n    <section id=\"j14\">\n        <h1>   Git(Distributed VCS) Vs SVN(centralized VCS)</h1>\n      \n      Installing git to local takes larger space than SVN and also SVN repo can handle large \n      binary files but git repo can't.<br>\nUsing git , the user will have the full version history of the remote repository in their \nlocal machine while with SVN only the files the user is working on r kept to the local .<br>\nThe git changes happen locally so the developer doesn't need to be connected to he internet \nall the time but with SVN user has to connected to the server to track changes &amp; development work.<br>\n____________<br>\nBitBucket ,SVN -> Free private repo<br>\nTravisCI .<br>\n\n  </section>\n    <section id=\"j15\">\n        <h1>     Gitlab over Github</h1>\n      The core difference is GitLab has Continuous Integration/Continuous Delivery (CI/CD) \n      and DevOps workflows built-in. GitHub lets you work with the CI/CD tools of your choice,\n       but you'll need to integrate them yourself. GitHub users typically work with a \n       third-party CI program such as Jenkins, CircleCI, or TravisCI<br>\n\n  </section>\n    <section id=\"j16\">\n        <h1>    Putty</h1>\n         Putty gives us an interface to connect to linux server. <br>It is a ssh client used ro make a secure connection with the server .<br>\n\n  </section>\n  <section id=\"j17\">\n        <h1>   Git Vs SourceTree</h1>\n         Sourcetree is a free graphical user interface (GUI) desktop client that simplifies how you \n      interact with Git repositories. Being  GUI based , it's easy to visualize ,mange repository \n      which is rather complex incase of command line tool like - git bash.It offers simplified \n      distributed version control<br>\nEfficient branching and merging\" and \"Fast\" are the key factors why developers consider Git; \nwhereas \"Visual history and branch view\", \"Beautiful UI\" and \"Easy repository browsing\" are \nthe primary reasons why SourceTree is favored.<br>\nCons of Git<br>\nEasy to lose uncommitted work<br>\nCons of source tree<br>\nExtremely slowly , fetching  data is often slow<br>\nCrashes often<br>\n\n  </section>\n  \n  </div>\n<b style=\"margin-left:200px\">Related Articles - <a href=\"https://interviewprepforinsiders.blogspot.com/2026/05/basic-shell-commands-of-unix-os.html\">Click here</a></b>\n<br>\n\n<script>\n\nwindow.addEventListener(\"load\", function () {\n\n    document.body.style.display = \"none\";\n\n    document.body.offsetHeight;\n\n    document.body.style.display = \"\";\n\n});\n\n</script>\n<hr><br>\n<!--\n<div class=\"fa\">\n  <h2>Frequently Asked Questions </h2></div>\n<div class=\"faq-sect\">\n\n\n<h3>What is DevOps?</h3>\n<p>\nDevOps is a software development approach that combines development and operations to improve deployment speed and software quality.\n</p>\n\n<h3>Which cloud platforms are important for interviews?</h3>\n<p>\nAWS, Microsoft Azure and Google Cloud Platform are the most commonly asked cloud platforms in interviews.\n</p>\n\n<h3>What tools are important in DevOps interviews?</h3>\n<p>\nDocker, Kubernetes, Jenkins, Git, Terraform and CI/CD pipeline tools are frequently discussed in DevOps interviews.\n</p>\n\n<h3>What is CI/CD in DevOps?</h3>\n<p>\nCI/CD stands for Continuous Integration and Continuous Deployment, which automate testing and software delivery processes.\n</p>\n\n<h3>R cloud computing questions asked in fresher's interview?</h3>\n<p>\nYes, freshers are often asked basic cloud concepts like virtualization, scalability, deployment models and cloud services.\n  </p></div>\n\n-->\n<!--\n<script>\ndocument.addEventListener(\"DOMContentLoaded\",function(){\n\nvar header=document.querySelector('.custom-header');\nvar menu=document.querySelector('.tabs-outer,.tabs-inner,.header-outer,nav,.menu');\n\nif(header && menu){\nmenu.parentNode.insertBefore(header,menu);\n}\n\n});\n</script>\n--><div class=\"blogger-post-footer\">Thankyou for visiting my page.Please ,add a comment and follow us.</div>"
}